MANIFEST.in
README.md
requirements.txt
setup.py
tsuruclient/__init__.py
tsuruclient/apps.py
tsuruclient/base.py
tsuruclient/client.py
tsuruclient/containers.py
tsuruclient/deploys.py
tsuruclient/events.py
tsuruclient/healings.py
tsuruclient/machines.py
tsuruclient/nodes.py
tsuruclient/plans.py
tsuruclient/pools.py
tsuruclient/templates.py
tsuruclient/users.py
tsuruclient.egg-info/PKG-INFO
tsuruclient.egg-info/SOURCES.txt
tsuruclient.egg-info/dependency_links.txt
tsuruclient.egg-info/requires.txt
tsuruclient.egg-info/top_level.txt