Metadata-Version: 1.0
Name: tsuruclient
Version: 0.4.1
Summary: Python client library for tsuru API
Home-page: https://github.com/tsuru/python-tsuruclient
Author: tsuru
Author-email: tsuru@corp.globo.com
License: UNKNOWN
Platform: UNKNOWN
